<?xml version="1.0" encoding="UTF-8"?>
<objects serializationModel="Studio.02.01.00">
	<object class="ParameterPreset" id="{898d6a58-d363-42f0-ab24-ca09fb58d969}">
		<property name="name">
			<value>Movement</value>
		</property>
		<relationship name="folder">
			<destination>{440427ff-7559-4a4a-a456-6783098799b9}</destination>
		</relationship>
		<relationship name="parameter">
			<destination>{b1963cc3-844b-4d3d-ac1c-19009913aa2f}</destination>
		</relationship>
	</object>
	<object class="GameParameter" id="{b1963cc3-844b-4d3d-ac1c-19009913aa2f}">
		<property name="initialValue">
			<value>0</value>
		</property>
		<property name="seekSpeed">
			<value>4.2000002861022949</value>
		</property>
		<property name="seekSpeedDescending">
			<value>5</value>
		</property>
		<property name="seekSpeedAsymmetric">
			<value>true</value>
		</property>
		<relationship name="modulators">
			<destination>{7dbdba4a-7931-4008-b03c-599db901acec}</destination>
		</relationship>
	</object>
	<object class="ADSRModulator" id="{7dbdba4a-7931-4008-b03c-599db901acec}">
		<property name="nameOfPropertyBeingModulated">
			<value>cursorPosition</value>
		</property>
	</object>
</objects>
